daisytuner_llvm/__init__.py
daisytuner_llvm/cli/__init__.py
daisytuner_llvm/codegen/__init__.py
daisytuner_llvm/codegen/generator.py
daisytuner_llvm/codegen/analysis/__init__.py
daisytuner_llvm/codegen/isl/__init__.py
daisytuner_llvm/scop/__init__.py
daisytuner_llvm/scop/ast.py
daisytuner_llvm/scop/scop.py
daisytuner_llvm/scop/types.py
daisytuner_llvm/scop/undefined_value.py
daisytuner_llvm/scop/value.py
daisytuner_llvm/scop/analysis/__init__.py
daisytuner_llvm/scop/analysis/undefined_access_to_indirection.py
daisytuner_llvm/scop/analysis/value_propagation.py
daisytuner_llvm/scop/computation/__init__.py
daisytuner_llvm/scop/computation/access.py
daisytuner_llvm/scop/computation/computation.py
daisytuner_llvm/scop/computation/indirection.py
daisytuner_llvm/scop/symbols/__init__.py
daisytuner_llvm/scop/symbols/constant.py
daisytuner_llvm/scop/symbols/loop.py
daisytuner_llvm/scop/symbols/memref.py
daisytuner_llvm/scop/symbols/parameter.py
daisytuner_llvm-0.1.2.dist-info/LICENSE
daisytuner_llvm-0.1.2.dist-info/METADATA
daisytuner_llvm-0.1.2.dist-info/WHEEL
daisytuner_llvm-0.1.2.dist-info/entry_points.txt
daisytuner_llvm-0.1.2.dist-info/top_level.txt
daisytuner_llvm-0.1.2.dist-info/RECORD
